Metadata-Version: 2.1
Name: base-qualitest-package
Version: 1.0.2
Summary: Qualitest package automation infrastructure kit tools for GUI and API tests
Home-page: https://upload.pypi.org/legacy/
Author: Yossi & Moshe
License: MIT
Platform: UNKNOWN
Classifier: Programming Language :: Python :: 3
Classifier: License :: OSI Approved :: MIT License
Classifier: Operating System :: OS Independent
Requires-Python: >=3.5
License-File: LICENCE
